pds/__init__.py
pds/__pycache__/__init__.cpython-39.pyc
pds/api/VERSION.txt
pds/api/__init__.py
pds/api/__pycache__/__init__.cpython-39.pyc
pds/api/tests/test_true.py
pds/api/tests/__pycache__/test_true.cpython-39-pytest-8.3.5.pyc
pds_api-15.1.0.dist-info/licenses/LICENSE.md
pds_api-15.1.0.dist-info/licenses/NOTICE.txt
pds_api-15.1.0.dist-info/METADATA
pds_api-15.1.0.dist-info/WHEEL
pds_api-15.1.0.dist-info/top_level.txt
pds_api-15.1.0.dist-info/zip-safe
pds_api-15.1.0.dist-info/RECORD
