Metadata-Version: 2.4
Name: pds-api
Version: 15.1.0
Summary: A short description, about 100-120 characters, suitable for search summaries
Home-page: https://github.com/NASA-PDS/pds-api
Download-URL: https://github.com/NASA-PDS/pds-api/releases/
Author: PDS
Author-email: pds_operator@jpl.nasa.gov
License: apache-2.0
Keywords: pds,planetary data,api
Classifier: Programming Language :: Python :: 3
Classifier: Programming Language :: Python :: 3.11
Classifier: License :: OSI Approved :: Apache Software License
Classifier: Operating System :: OS Independent
Requires-Python: >=3.9
License-File: LICENSE.md
License-File: NOTICE.txt
Provides-Extra: dev
Requires-Dist: pydocstyle~=6.1.1; extra == "dev"
Requires-Dist: pytest~=8.3.3; extra == "dev"
Requires-Dist: sphinx~=7.4.7; extra == "dev"
Requires-Dist: sphinx-rtd-theme~=3.0.1; extra == "dev"
Requires-Dist: sphinxcontrib-openapi~=0.7.0; extra == "dev"
Requires-Dist: sphinxcontrib-redoc~=1.6.0; extra == "dev"
Requires-Dist: sphinx-prompt~=1.8.0; extra == "dev"
Requires-Dist: Sphinx-Substitution-Extensions==2022.2.16; extra == "dev"
Requires-Dist: sphinx-copybutton~=0.5.0; extra == "dev"
Requires-Dist: tox~=4.23.0; extra == "dev"
Dynamic: download-url
Dynamic: license-file
